Workbook

Sheet 投资组合概览
A1: 📊 投资组合总览
A3: 更新日期 | B3: =TODAY()
A5: 总资产 | B5: =SUM(黄金持仓!E2:E3)+SUM(基金持仓!D2:D6) | C5: 总投入 | D5: =SUM(黄金持仓!F2:F3)+SUM(基金持仓!E2:E6) | E5: 总盈亏 | F5: =B5-D5 | G5: 总收益率 | H5: =F5/D5
A7: 资产分布
A8: 资产类别 | B8: 市值 | C8: 占比 | D8: 盈亏 | E8: 收益率 | F8: 操作建议
A9: 黄金 | B9: =SUM(黄金持仓!E2:E3) | C9: =B9/$B$5 | D9: =SUM(黄金持仓!G2:G3) | E9: =D9/SUM(黄金持仓!F2:F3) | F9: 波段操作
A10: 偏股基金 | B10: =SUMIF(基金持仓!C:C,"偏股",基金持仓!D:D)+SUMIF(基金持仓!C:C,"指数",基金持仓!D:D) | C10: =B10/$B$5 | D10: =SUMIF(基金持仓!C:C,"偏股",基金持仓!F:F)+SUMIF(基金持仓!C:C,"指数",基金持仓!F:F) | E10: =D10/(SUMIF(基金持仓!C:C,"偏股",基金持仓!E:E)+SUMIF(基金持仓!C:C,"指数",基金持仓!E:E)) | F10: 逢高减仓
A11: 海外指数 | B11: =SUMIF(基金持仓!C:C,"海外",基金持仓!D:D) | C11: =B11/$B$5 | D11: =SUMIF(基金持仓!C:C,"海外",基金持仓!F:F) | E11: =D11/SUMIF(基金持仓!C:C,"海外",基金持仓!E:E) | F11: 继续定投
A12: 资源/周期 | B12: =SUMIF(基金持仓!C:C,"周期",基金持仓!D:D) | C12: =B12/$B$5 | D12: =SUMIF(基金持仓!C:C,"周期",基金持仓!F:F) | E12: =D12/SUMIF(基金持仓!C:C,"周期",基金持仓!E:E) | F12: 持有观察

Sheet 黄金持仓
A1: 🥇 黄金持仓明细
A2: 账户 | B2: 持有克数 | C2: 成本均价(元/克) | D2: 当前金价(元/克) | E2: 当前市值 | F2: 成本总额 | G2: 持有收益 | H2: 收益率
A3: 支付宝黄金 | B3: 74.3126 | C3: 1162 | D3: =黄金价格!B2 | E3: =B3*D3 | F3: =B3*C3 | G3: =E3-F3 | H3: =G3/F3
A4: 京东金融黄金 | B4: 31.5408 | C4: 973.4 | D4: =黄金价格!B2 | E4: =B4*D4 | F4: =B4*C4 | G4: =E4-F4 | H4: =G4/F4
A5: 合计 | B5: =SUM(B3:B4) | E5: =SUM(E3:E4) | F5: =SUM(F3:F4) | G5: =SUM(G3:G4) | H5: =G5/F5
A7: 📈 京东波段账户交易计划
A8: 策略类型 | B8: 网格波段交易
A9: 网格区间 | B9: 850 - 950 元/克
A10: 网格间距 | B10: 20 元/克
A11: 每格交易量 | B11: 5 克
A12: 当前持仓 | B12: =B4
A13: 当前信号 | B13: =IF(D2<=870,"🟢 接近下沿，可小仓买入",IF(D2>=930,"🔴 接近上沿，可减仓卖出","🟡 震荡区间，持有观察"))

Sheet 基金持仓
A1: 📈 基金持仓明细
A2: 基金名称 | B2: 代码 | C2: 类别 | D2: 当前市值 | E2: 成本总额 | F2: 持有收益 | G2: 收益率 | H2: 操作建议
A3: 中航机遇领航混合C | B3: 018957 | C3: 偏股 | D3: 7128.78 | E3: 9554.98 | F3: =D3-E3 | G3: =F3/E3 | H3: 逢高减仓60%
A4: 永赢先锋半导体智选混合C | B4: 025209 | C4: 偏股 | D4: 3300.59 | E4: 4582.08 | F4: =D4-E4 | G4: =F4/E4 | H4: 逢高减仓70%
A5: 东财中证通信技术主题指数C | B5: 008327 | C5: 指数 | D5: 1218.19 | E5: 1676.35 | F5: =D5-E5 | G5: =F5/E5 | H5: 反弹清仓
A6: 中欧资源精选混合C | B6: 023037 | C6: 周期 | D6: 3622.49 | E6: 3981.14 | F6: =D6-E6 | G6: =F6/E6 | H6: 持有观察
A7: 广发纳斯达克100ETF联接C | B7: 006479 | C7: 海外 | D7: 12421.46 | E7: 10190 | F7: =D7-E7 | G7: =F7/E7 | H7: 继续定投
A8: 合计 | D8: =SUM(D3:D7) | E8: =SUM(E3:E7) | F8: =SUM(F3:F7) | G8: =F8/E8

Sheet 黄金价格
A1: 日期 | B1: 上海金收盘价(元/克) | C1: 伦敦金(美元/盎司)
A2: =TODAY() | B2: 886 | C2: 4052.6

Sheet 交易记录
A1: 日期 | B1: 品种 | C1: 操作 | D1: 数量 | E1: 价格 | F1: 金额 | G1: 盈亏 | H1: 备注
A2: 暂无交易记录
